runner/__init__.py
runner/main.py
scripts/run_sanity_checks.py
tropt/__init__.py
tropt/common.py
tropt/attack_zoo/BEAST.py
tropt/attack_zoo/GASLITE.py
tropt/attack_zoo/GASLITEPlus.py
tropt/attack_zoo/GCG.py
tropt/attack_zoo/GCGEmb.py
tropt/attack_zoo/GCGMult.py
tropt/attack_zoo/GCGRand.py
tropt/attack_zoo/LASTLITE.py
tropt/attack_zoo/RAL.py
tropt/attack_zoo/__init__.py
tropt/loss/__init__.py
tropt/loss/base.py
tropt/loss/utils.py
tropt/models/__init__.py
tropt/models/base.py
tropt/models/inputs.py
tropt/models/google/__init__.py
tropt/models/google/encoder.py
tropt/models/huggingface/__init__.py
tropt/models/huggingface/base.py
tropt/models/huggingface/encoder.py
tropt/models/huggingface/lm.py
tropt/models/vllm/__init__.py
tropt/models/vllm/lm.py
tropt/optimizer/__init__.py
tropt/optimizer/base.py
tropt/optimizer/beast_optimizer.py
tropt/optimizer/gaslite_optimizer.py
tropt/optimizer/gasliteplus_optimizer.py
tropt/optimizer/gcg_optimizer.py
tropt/optimizer/laslite_optimizer.py
tropt/optimizer/prs_optimizer.py
tropt/optimizer/ral_optimizer.py
tropt/optimizer/super_optimizer.py
tropt/optimizer/utils/__init__.py
tropt/optimizer/utils/beast_utils.py
tropt/optimizer/utils/buffer.py
tropt/optimizer/utils/retokenization.py
tropt/optimizer/utils/token_constraints.py
tropt/optimizer/utils/token_initializers.py
tropt/tracker/__init__.py
tropt/tracker/base.py
tropt/utils/utils.py
tropt-0.0.1a1.dist-info/licenses/LICENSE
tropt-0.0.1a1.dist-info/METADATA
tropt-0.0.1a1.dist-info/WHEEL
tropt-0.0.1a1.dist-info/top_level.txt
tropt-0.0.1a1.dist-info/RECORD
