Metadata-Version: 2.4
Name: tropt
Version: 0.0.1a1
Summary: A toolbox for optimizing discrete text triggers.
Author: Matan Ben-Tov
License: MIT
Project-URL: Repository, https://github.com/matanbt/tropt
Project-URL: Issues, https://github.com/matanbt/tropt/issues
Requires-Python: >=3.10
License-File: LICENSE
Requires-Dist: torch>=2.4.0
Requires-Dist: tqdm
Requires-Dist: jaxtyping
Requires-Dist: numpy>=2.0.0
Requires-Dist: transformers>=4.45.0
Requires-Dist: accelerate>=1.0.0
Requires-Dist: hydra-core>=1.3.0
Requires-Dist: omegaconf
Requires-Dist: sentence-transformers>=5.1.0
Requires-Dist: wandb
Requires-Dist: livelossplot
Requires-Dist: openai
Provides-Extra: dev
Requires-Dist: pytest; extra == "dev"
Requires-Dist: ruff; extra == "dev"
Requires-Dist: pre-commit; extra == "dev"
Dynamic: license-file
